{
  "parent": "minecraft:recipes/root",
  "criteria": {
    "has_raw_neron": {
      "conditions": {
        "items": [
          {
            "items": [
              "echoes:raw_neron"
            ]
          }
        ]
      },
      "trigger": "minecraft:inventory_changed"
    }
  },
  "requirements": [
    [
      "has_raw_neron"
    ]
  ],
  "rewards": {
    "recipes": [
      "echoes:neron_block_from_blasting_raw_neron_block",
      "echoes:neron_block_from_smelting_raw_neron_block",
      "echoes:neron_ingot_from_blasting_raw_neron",
      "echoes:neron_ingot_from_smelting_raw_neron",
      "echoes:umbrelith_furnace_neron_ingot_from_raw_neron"
    ]
  },
  "sends_telemetry_event": false
}